toyai/ETL.py
toyai/Trainer.py
toyai/__init__.py
toyai/cli.py
toyai/tools/FileText.py
toyai/tools/__init__.py
toyai/tools/os.py
toyai/tools/txt.py
toyai-0.2.3.dist-info/METADATA
toyai-0.2.3.dist-info/WHEEL
toyai-0.2.3.dist-info/entry_points.txt
toyai-0.2.3.dist-info/top_level.txt
toyai-0.2.3.dist-info/RECORD
