Metadata-Version: 2.1
Name: toyai
Version: 0.2.3
Summary: A description of your package
Author: Supanut Panyagosa
Author-email: supanut.pgs@gmail.com
Classifier: Programming Language :: Python :: 3
Classifier: License :: OSI Approved :: MIT License
Classifier: Operating System :: OS Independent
Requires-Python: >=3.6
